README.md
setup.py
PyaiVS/DNN_model.py
PyaiVS/KNN_model.py
PyaiVS/RF_model.py
PyaiVS/SVM_model.py
PyaiVS/XGB_model.py
PyaiVS/__init__.py
PyaiVS/compute_info.py
PyaiVS/data_utils.py
PyaiVS/dl_screener.py
PyaiVS/dnn_need.py
PyaiVS/dnn_pred_bigscale.py
PyaiVS/dnn_pred_bigscale_gpu.py
PyaiVS/dnn_screener.py
PyaiVS/dnn_torch_utils.py
PyaiVS/feature_create.py
PyaiVS/gnn_utils.py
PyaiVS/graph_model.py
PyaiVS/ml_screener.py
PyaiVS/model_bulid.py
PyaiVS/real_auc.py
PyaiVS/run_dl.py
PyaiVS/run_ml.py
PyaiVS/run_model.py
PyaiVS/run_result.py
PyaiVS/screen_dnn.py
PyaiVS/splitdater.py
PyaiVS/virtual_screen.py
PyaiVS.egg-info/PKG-INFO
PyaiVS.egg-info/SOURCES.txt
PyaiVS.egg-info/dependency_links.txt
PyaiVS.egg-info/top_level.txt