Metadata-Version: 2.1
Name: PyaiVS
Version: 1.1.6
Summary: model_bulid & vitual_screen
Home-page: 
Author: bokey
Author-email: 
Classifier: Development Status :: 3 - Alpha
Classifier: Intended Audience :: Developers
Classifier: Topic :: Software Development :: Build Tools
Classifier: License :: OSI Approved :: MIT License
Classifier: Programming Language :: Python :: 3
Requires-Python: >=3
